bioprocess_intelligence/__init__.py
bioprocess_intelligence/client.py
bioprocess_intelligence/config.py
bioprocess_intelligence/formatters.py
bioprocess_intelligence/fragments.py
bioprocess_intelligence/import_functions.py
bioprocess_intelligence/import_json.py
bioprocess_intelligence/import_yaml.py
bioprocess_intelligence-0.2.0.dist-info/licenses/LICENSE
bioprocess_intelligence-0.2.0.dist-info/METADATA
bioprocess_intelligence-0.2.0.dist-info/WHEEL
bioprocess_intelligence-0.2.0.dist-info/top_level.txt
bioprocess_intelligence-0.2.0.dist-info/RECORD
