Metadata-Version: 2.4
Name: bioprocess_intelligence
Version: 0.2.0
Summary: A Python client for interacting with the Bioprocess Intelligence platform
Author: WisdomEngine GmbH
Author-email: support@wisdomengine.de
License: Proprietary - Free for academic use, commercial license required
Classifier: Programming Language :: Python :: 3
Classifier: Operating System :: OS Independent
Classifier: Intended Audience :: Developers
Classifier: Intended Audience :: Science/Research
Classifier: Topic :: Scientific/Engineering :: Bio-Informatics
Classifier: License :: Other/Proprietary License
Requires-Python: >=3.8
License-File: LICENSE
Requires-Dist: requests>=2.31.0
Requires-Dist: python-dotenv>=1.0.0
Requires-Dist: pyyaml>=6.0.1
Requires-Dist: tabulate>=0.9.0
Requires-Dist: backoff>=2.2.1
Requires-Dist: gql>=3.5.2
Requires-Dist: graphql-core>=3.2.4
Requires-Dist: openpyxl>=3.1.5
Requires-Dist: propcache>=0.3.0
Requires-Dist: roman-numerals-py>=3.1.0
Requires-Dist: requests-toolbelt>=1.0.0
Requires-Dist: beautifulsoup4>=4.13.0
Requires-Dist: typing_extensions>=4.12.0
Requires-Dist: anyio>=4.0.0
Provides-Extra: dev
Requires-Dist: pytest>=8.0.0; extra == "dev"
Requires-Dist: pytest-cov>=4.0.0; extra == "dev"
Requires-Dist: sphinx>=8.0.0; extra == "dev"
Requires-Dist: furo>=2024.8.0; extra == "dev"
Requires-Dist: sphinx-basic-ng>=1.0.0b2; extra == "dev"
Requires-Dist: sphinxcontrib-applehelp>=2.0.0; extra == "dev"
Requires-Dist: sphinxcontrib-devhelp>=2.0.0; extra == "dev"
Requires-Dist: sphinxcontrib-htmlhelp>=2.1.0; extra == "dev"
Requires-Dist: sphinxcontrib-jsmath>=1.0.1; extra == "dev"
Requires-Dist: sphinxcontrib-qthelp>=2.0.0; extra == "dev"
Requires-Dist: sphinxcontrib-serializinghtml>=2.0.0; extra == "dev"
Requires-Dist: Pygments>=2.19.0; extra == "dev"
Dynamic: author
Dynamic: author-email
Dynamic: classifier
Dynamic: description
Dynamic: description-content-type
Dynamic: license
Dynamic: license-file
Dynamic: provides-extra
Dynamic: requires-dist
Dynamic: requires-python
Dynamic: summary
